{
	"credit": "Made with Blockbench",
	"textures": {
		"0": "minecraft:block/polished_blackstone",
		"1": "minecraft:block/raw_gold_block",
		"particle": "minecraft:block/polished_blackstone"
	},
	"elements": [
		{
			"from": [7, 0, 9],
			"to": [9, 18, 11],
			"faces": {
				"north": {"uv": [0, 0, 2, 16], "texture": "#0"},
				"east": {"uv": [0, 0, 2, 16], "texture": "#0"},
				"south": {"uv": [0, 0, 2, 16], "texture": "#0"},
				"west": {"uv": [0, 0, 2, 16], "texture": "#0"},
				"up": {"uv": [0, 0, 2, 2], "texture": "#missing"},
				"down": {"uv": [0, 0, 2, 2], "texture": "#0"}
			}
		},
		{
			"from": [6, 18, 9],
			"to": [10, 19, 11],
			"faces": {
				"north": {"uv": [0, 0, 4, 1], "texture": "#1"},
				"east": {"uv": [0, 0, 2, 1], "texture": "#1"},
				"south": {"uv": [0, 0, 4, 1], "texture": "#1"},
				"west": {"uv": [0, 0, 2, 1], "texture": "#1"},
				"up": {"uv": [0, 0, 4, 2], "texture": "#1"},
				"down": {"uv": [0, 0, 4, 2], "texture": "#1"}
			}
		},
		{
			"from": [5, 19, 9],
			"to": [6, 26, 11],
			"faces": {
				"north": {"uv": [0, 0, 1, 7], "texture": "#1"},
				"east": {"uv": [0, 0, 2, 7], "texture": "#1"},
				"south": {"uv": [0, 0, 1, 7], "texture": "#1"},
				"west": {"uv": [0, 0, 2, 7], "texture": "#1"},
				"up": {"uv": [0, 0, 1, 2], "texture": "#1"},
				"down": {"uv": [0, 0, 1, 2], "texture": "#1"}
			}
		},
		{
			"from": [10, 19, 9],
			"to": [11, 26, 11],
			"faces": {
				"north": {"uv": [0, 0, 1, 7], "texture": "#1"},
				"east": {"uv": [0, 0, 2, 7], "texture": "#1"},
				"south": {"uv": [0, 0, 1, 7], "texture": "#1"},
				"west": {"uv": [0, 0, 2, 7], "texture": "#1"},
				"up": {"uv": [0, 0, 1, 2], "texture": "#1"},
				"down": {"uv": [0, 0, 1, 2], "texture": "#1"}
			}
		}
	],
	"display": {
		"firstperson_righthand": {
			"translation": [0, -4.25, 0]
		},
		"firstperson_lefthand": {
			"translation": [0, -4.25, 0]
		},
		"gui": {
			"rotation": [0, 0, 42]
		},
		"fixed": {
			"translation": [0, -2.5, -3]
		}
	},
	"groups": [
		{
			"name": "stick",
			"origin": [8, 8, 8],
			"color": 0,
			"children": [0]
		},
		{
			"name": "staff/prongs?",
			"origin": [8, 8, 8],
			"color": 0,
			"children": [1, 2, 3]
		}
	]
}